{
    "files": {
        "work_dir": "__HOME__/",
        "mc_folder": "__HOME__/.minecraft",
        "save_folder": "__WORKDIR__/saves",
        "data_folder": "__WORKDIR__/data",
        "name_file": "__WORKDIR__/names.txt",
        "char_file": "__WORKDIR__/chars.json",
        "video_file": "__WORKDIR__/record.mp4"
    },
    "resolution": {
        "x": 175,
        "y": 175
    },
    "chat_chars_limit": 512,
    "frame_record_limit": 1000,
    "port": 8000,
    "version": "1.18.1",
    "threshold": {
        "distance": 10.0,
        "direction": 30.0
    }
}